{
  "publicPath": "",
  "all": [
    "assets/1.js",
    "assets/10.js",
    "assets/11.js",
    "assets/12.js",
    "assets/13.js",
    "assets/14.js",
    "assets/15.js",
    "assets/16.js",
    "assets/17.js",
    "assets/18.js",
    "assets/19.js",
    "assets/2.js",
    "assets/20.js",
    "assets/21.js",
    "assets/22.js",
    "assets/23.js",
    "assets/24.js",
    "assets/25.js",
    "assets/26.js",
    "assets/3.js",
    "assets/4.js",
    "assets/5.js",
    "assets/6.js",
    "assets/7.js",
    "assets/8.js",
    "assets/9.js",
    "assets/main.js"
  ],
  "initial": [
    "assets/main.js"
  ],
  "async": [
    "assets/1.js",
    "assets/10.js",
    "assets/11.js",
    "assets/12.js",
    "assets/13.js",
    "assets/14.js",
    "assets/15.js",
    "assets/16.js",
    "assets/17.js",
    "assets/18.js",
    "assets/19.js",
    "assets/2.js",
    "assets/20.js",
    "assets/21.js",
    "assets/22.js",
    "assets/23.js",
    "assets/24.js",
    "assets/25.js",
    "assets/26.js",
    "assets/3.js",
    "assets/4.js",
    "assets/5.js",
    "assets/6.js",
    "assets/7.js",
    "assets/8.js",
    "assets/9.js"
  ],
  "modules": {
    "28478931": [
      24
    ],
    "35017463": [
      1
    ],
    "47776739": [
      5
    ],
    "47943859": [
      14
    ],
    "53239738": [
      8
    ],
    "89196834": [
      22
    ],
    "187d9f2a": [
      26
    ],
    "07ded48f": [
      26
    ],
    "4168f0ca": [
      26
    ],
    "67595e8c": [
      26
    ],
    "6510b0ac": [
      26
    ],
    "5adefef0": [
      26
    ],
    "8f5e35fe": [
      26
    ],
    "728fdbff": [
      26
    ],
    "389a0352": [
      26
    ],
    "5e9c95b4": [
      26
    ],
    "72adb43c": [
      26
    ],
    "3a38253a": [
      26
    ],
    "3b007ad6": [
      26
    ],
    "6f92c30c": [
      26
    ],
    "513084dc": [
      26
    ],
    "736fa528": [
      26
    ],
    "db7ec3f8": [
      26
    ],
    "734c515f": [
      26
    ],
    "2bd0cf71": [
      26
    ],
    "f010bbb8": [
      26
    ],
    "54726dc6": [
      26
    ],
    "51a2c5a4": [
      26
    ],
    "77837dcc": [
      26
    ],
    "75ba4c5c": [
      26
    ],
    "a0ff5db4": [
      26
    ],
    "96b7e30e": [
      26
    ],
    "318708f2": [
      26
    ],
    "552672fc": [
      26
    ],
    "1f679448": [
      26
    ],
    "68224a32": [
      26
    ],
    "b95d65ec": [
      26
    ],
    "83eaf2ac": [
      26
    ],
    "6be6fb96": [
      26
    ],
    "e778598a": [
      26
    ],
    "244acc76": [
      26
    ],
    "0143b556": [
      26
    ],
    "1c6fa192": [
      26
    ],
    "054d5ef8": [
      26
    ],
    "59ba5e2e": [
      26
    ],
    "b4ba51ae": [
      26
    ],
    "6e7ff9a9": [
      26
    ],
    "79a2a098": [
      26
    ],
    "2f03fc64": [
      26
    ],
    "04f3ba74": [
      26
    ],
    "8fa5bf30": [
      26
    ],
    "1619bd1e": [
      26
    ],
    "14901c44": [
      26
    ],
    "17c9c4cd": [
      26
    ],
    "0b94b2d4": [
      26
    ],
    "753d51a9": [
      26
    ],
    "4ea892a7": [
      26
    ],
    "011ac13d": [
      26
    ],
    "7fde518a": [
      18
    ],
    "9a0de834": [
      20
    ],
    "5cb2f360": [
      20
    ],
    "5a98bb58": [
      0
    ],
    "ecdba542": [
      0
    ],
    "7b4ba7f4": [
      0
    ],
    "1ffb5f8a": [
      25
    ],
    "72c2affd": [
      1
    ],
    "1a235f6c": [
      2
    ],
    "ca1e7a24": [
      3
    ],
    "f0afd2b2": [
      21
    ],
    "0255be0b": [
      11
    ],
    "a86d7996": [
      4
    ],
    "2af868d3": [
      5
    ],
    "b9ce9242": [
      22
    ],
    "442dc05a": [
      23
    ],
    "0bc88acb": [
      24
    ],
    "ac507964": [
      6
    ],
    "1ba9dcd3": [
      19
    ],
    "08d94006": [
      9
    ],
    "3aa14098": [
      7
    ],
    "5a6a9a52": [
      8
    ],
    "71b2f535": [
      10
    ],
    "3b66f87a": [
      12
    ],
    "69ecc278": [
      13
    ],
    "82e136ce": [
      16
    ],
    "12858ede": [
      15
    ],
    "4a2b7512": [
      17
    ],
    "60e7d915": [
      18
    ],
    "5500e3c2": [
      18
    ],
    "dee49788": [
      20
    ],
    "39890b40": [
      20
    ],
    "5d57a4ad": [
      20
    ],
    "11a3fe3a": [
      20
    ],
    "15ed2532": [
      20
    ],
    "76fe00fc": [
      0
    ],
    "b3eeb184": [
      0
    ],
    "07e5891e": [
      0
    ],
    "55fbcd76": [
      0
    ],
    "2b06ad78": [
      0
    ],
    "303cb2ce": [
      0
    ],
    "13a221fb": [
      0
    ],
    "759c1895": [
      25
    ],
    "3116f682": [
      25
    ],
    "9226b654": [
      1
    ],
    "79376a24": [
      2
    ],
    "417280d1": [
      2
    ],
    "994a6370": [
      3
    ],
    "592aedb5": [
      3
    ],
    "2dbcb381": [
      21
    ],
    "bffaa8a4": [
      21
    ],
    "8b8a131e": [
      11
    ],
    "1c14e0e4": [
      11
    ],
    "4d2ef3ca": [
      4
    ],
    "e56d3464": [
      4
    ],
    "1df074ac": [
      5
    ],
    "492d53b9": [
      22
    ],
    "2b7b4598": [
      23
    ],
    "5c885561": [
      23
    ],
    "027ed2b8": [
      24
    ],
    "1c5233b0": [
      6
    ],
    "aaa73d56": [
      6
    ],
    "58e1d58e": [
      19
    ],
    "3568ffac": [
      19
    ],
    "2932a2e3": [
      9
    ],
    "45d8fad4": [
      9
    ],
    "5907e072": [
      7
    ],
    "6be80bc2": [
      7
    ],
    "6f8f13eb": [
      8
    ],
    "116684e2": [
      10
    ],
    "9a70c908": [
      10
    ],
    "b6e96fae": [
      12
    ],
    "2676789c": [
      12
    ],
    "5152b89e": [
      13
    ],
    "198dcf4b": [
      13
    ],
    "24ae559a": [
      14
    ],
    "5feecd60": [
      14
    ],
    "76749cff": [
      16
    ],
    "4f62f11c": [
      16
    ],
    "133c36f7": [
      15
    ],
    "2c95772c": [
      15
    ],
    "689214ec": [
      17
    ],
    "4cd3a2ce": [
      17
    ],
    "7a85e46c": [
      7
    ],
    "8a2f17a6": [
      25
    ],
    "e1701426": [
      9
    ],
    "104cf744": [
      17
    ],
    "48fdef7c": [
      2
    ],
    "44903d7e": [
      15
    ],
    "55b513e0": [
      3
    ],
    "46fd8fd9": [
      21
    ],
    "96d89b6e": [
      16
    ],
    "e32a468a": [
      11
    ],
    "26395dad": [
      1
    ],
    "54a9d5b6": [
      4
    ],
    "4161eafa": [
      5
    ],
    "26a3f2f6": [
      13
    ],
    "7c9427de": [
      22
    ],
    "423c9c73": [
      12
    ],
    "114b970c": [
      23
    ],
    "1f4d0e27": [
      10
    ],
    "34e4c87b": [
      24
    ],
    "5779a300": [
      6
    ],
    "083d907c": [
      8
    ],
    "776abf83": [
      19
    ],
    "e54cbaea": [
      14
    ],
    "41e566a6": [
      0
    ],
    "15431eed": [
      18
    ],
    "ce980fdc": [
      20
    ]
  }
}