{
  "publicPath": "",
  "all": [
    "assets/1.js",
    "assets/10.js",
    "assets/11.js",
    "assets/12.js",
    "assets/13.js",
    "assets/14.js",
    "assets/15.js",
    "assets/16.js",
    "assets/17.js",
    "assets/18.js",
    "assets/19.js",
    "assets/2.js",
    "assets/20.js",
    "assets/21.js",
    "assets/22.js",
    "assets/23.js",
    "assets/24.js",
    "assets/25.js",
    "assets/26.js",
    "assets/3.js",
    "assets/4.js",
    "assets/5.js",
    "assets/6.js",
    "assets/7.js",
    "assets/8.js",
    "assets/9.js",
    "assets/main.js"
  ],
  "initial": [
    "assets/main.js"
  ],
  "async": [
    "assets/1.js",
    "assets/10.js",
    "assets/11.js",
    "assets/12.js",
    "assets/13.js",
    "assets/14.js",
    "assets/15.js",
    "assets/16.js",
    "assets/17.js",
    "assets/18.js",
    "assets/19.js",
    "assets/2.js",
    "assets/20.js",
    "assets/21.js",
    "assets/22.js",
    "assets/23.js",
    "assets/24.js",
    "assets/25.js",
    "assets/26.js",
    "assets/3.js",
    "assets/4.js",
    "assets/5.js",
    "assets/6.js",
    "assets/7.js",
    "assets/8.js",
    "assets/9.js"
  ],
  "modules": {
    "27678136": [
      13
    ],
    "34315892": [
      25
    ],
    "48889980": [
      13
    ],
    "49463450": [
      0
    ],
    "65976159": [
      7
    ],
    "91630b1a": [
      26
    ],
    "ce38bd74": [
      26
    ],
    "e46c097e": [
      26
    ],
    "b54d019c": [
      26
    ],
    "22c6594e": [
      26
    ],
    "07857a19": [
      26
    ],
    "408f1025": [
      26
    ],
    "2ad824b6": [
      26
    ],
    "cdea3f8a": [
      26
    ],
    "681d152e": [
      26
    ],
    "2dfedbaa": [
      26
    ],
    "a84fed20": [
      26
    ],
    "5507540c": [
      26
    ],
    "37ee20be": [
      26
    ],
    "4ebb68c5": [
      26
    ],
    "555ea468": [
      26
    ],
    "0c060a00": [
      26
    ],
    "1bfb8edb": [
      26
    ],
    "56ffe626": [
      26
    ],
    "6972e568": [
      26
    ],
    "3ba1da3e": [
      26
    ],
    "09632228": [
      26
    ],
    "234de1cf": [
      26
    ],
    "5e77f900": [
      26
    ],
    "1088e64f": [
      26
    ],
    "258d0596": [
      26
    ],
    "7afa4ff0": [
      26
    ],
    "56a4a750": [
      26
    ],
    "4ecc9300": [
      26
    ],
    "ecf643e4": [
      26
    ],
    "76983e34": [
      26
    ],
    "4f0f5361": [
      26
    ],
    "ff32e69e": [
      26
    ],
    "ed109b82": [
      26
    ],
    "3fe6ebf2": [
      26
    ],
    "3933f3d1": [
      26
    ],
    "515feac8": [
      26
    ],
    "1a34a3fc": [
      26
    ],
    "405b42ed": [
      26
    ],
    "410eb4b6": [
      26
    ],
    "4ffe7233": [
      26
    ],
    "f3b47a84": [
      26
    ],
    "6a216acc": [
      26
    ],
    "7948a0d0": [
      26
    ],
    "55eb4872": [
      26
    ],
    "ddd96ea6": [
      26
    ],
    "c4706a0c": [
      26
    ],
    "497f40e0": [
      26
    ],
    "59f88516": [
      26
    ],
    "44f3e4c5": [
      26
    ],
    "b8bd7476": [
      26
    ],
    "c9d5d14e": [
      26
    ],
    "617041af": [
      18
    ],
    "a724a64c": [
      20
    ],
    "2ea05b54": [
      20
    ],
    "e08f8e38": [
      0
    ],
    "829caa2a": [
      0
    ],
    "4d390fe8": [
      0
    ],
    "0b358388": [
      25
    ],
    "118d0448": [
      1
    ],
    "1f647bea": [
      2
    ],
    "838a6f22": [
      3
    ],
    "0086bfe8": [
      21
    ],
    "258aedea": [
      11
    ],
    "2477d558": [
      4
    ],
    "6422309c": [
      5
    ],
    "1bf76020": [
      22
    ],
    "85e72cca": [
      23
    ],
    "a281ecac": [
      24
    ],
    "375d9b8f": [
      6
    ],
    "3edf0cb2": [
      19
    ],
    "3d8e321c": [
      9
    ],
    "19bcdd71": [
      8
    ],
    "7c15e336": [
      10
    ],
    "66c351a2": [
      12
    ],
    "6f2ddef6": [
      13
    ],
    "7f1a3ccc": [
      14
    ],
    "3c76d710": [
      16
    ],
    "cc989120": [
      15
    ],
    "752195d3": [
      17
    ],
    "c2721ee2": [
      18
    ],
    "c636df2c": [
      18
    ],
    "307647b8": [
      20
    ],
    "43ca63ba": [
      20
    ],
    "cfc03a56": [
      20
    ],
    "47f08b98": [
      20
    ],
    "01c5698f": [
      20
    ],
    "646992fe": [
      0
    ],
    "381b43f8": [
      0
    ],
    "1a4cc249": [
      0
    ],
    "12ebd00b": [
      0
    ],
    "0abf2270": [
      0
    ],
    "205e1e23": [
      0
    ],
    "4106a51c": [
      25
    ],
    "755fbafc": [
      1
    ],
    "7ab14d01": [
      1
    ],
    "1430f0eb": [
      2
    ],
    "03a064c6": [
      2
    ],
    "760dbf4f": [
      3
    ],
    "476fa86a": [
      3
    ],
    "0f777ec8": [
      21
    ],
    "10038d23": [
      21
    ],
    "26d2eb0a": [
      11
    ],
    "43dc59e2": [
      11
    ],
    "7b4f8a74": [
      4
    ],
    "7284af39": [
      4
    ],
    "c5d3f65c": [
      5
    ],
    "a3e87c52": [
      5
    ],
    "2ae81f00": [
      22
    ],
    "2b742d5b": [
      22
    ],
    "6805af0a": [
      23
    ],
    "66ed9254": [
      23
    ],
    "7de626ca": [
      24
    ],
    "e2483862": [
      24
    ],
    "46dd0b22": [
      6
    ],
    "0382fdca": [
      6
    ],
    "402709d2": [
      19
    ],
    "11341c52": [
      19
    ],
    "69ccb188": [
      9
    ],
    "7b6267fe": [
      9
    ],
    "03649f8e": [
      7
    ],
    "b9b5cdd8": [
      7
    ],
    "88dd9ade": [
      8
    ],
    "660bc256": [
      8
    ],
    "7a916bd4": [
      10
    ],
    "6797f8b1": [
      10
    ],
    "362ce27c": [
      12
    ],
    "2b89be72": [
      12
    ],
    "6138bf0c": [
      14
    ],
    "6020a256": [
      14
    ],
    "39e6dcd0": [
      16
    ],
    "cb690cc6": [
      16
    ],
    "68dad490": [
      15
    ],
    "79d09195": [
      15
    ],
    "0dd7e4b3": [
      17
    ],
    "9aa164e4": [
      17
    ],
    "4433ee37": [
      7
    ],
    "78c8ee4c": [
      25
    ],
    "c6111240": [
      9
    ],
    "dc78509e": [
      17
    ],
    "1d82e62e": [
      2
    ],
    "00519ff4": [
      15
    ],
    "1f77ebe6": [
      3
    ],
    "79a7aec6": [
      21
    ],
    "b72de408": [
      16
    ],
    "7e40386e": [
      11
    ],
    "68ab0140": [
      1
    ],
    "394ad3d0": [
      4
    ],
    "01e8c936": [
      5
    ],
    "6236df3a": [
      13
    ],
    "173fea04": [
      22
    ],
    "30a483b4": [
      12
    ],
    "43f5b5f9": [
      23
    ],
    "280022d4": [
      10
    ],
    "577e872e": [
      24
    ],
    "eefef626": [
      6
    ],
    "41f3d496": [
      8
    ],
    "67401b36": [
      19
    ],
    "7ff87d10": [
      14
    ],
    "fc123474": [
      0
    ],
    "b2a17ae6": [
      18
    ],
    "4e75119c": [
      20
    ]
  }
}